zipcodestack/__init__.py
zipcodestack/client.py
zipcodestack-0.1.1.dist-info/licenses/LICENSE
zipcodestack-0.1.1.dist-info/METADATA
zipcodestack-0.1.1.dist-info/WHEEL
zipcodestack-0.1.1.dist-info/top_level.txt
zipcodestack-0.1.1.dist-info/RECORD
