Metadata-Version: 2.4
Name: zipcodestack
Version: 0.1.1
Summary: Official Python client for zipcodestack.com API
Home-page: https://zipcodestack.com/docs/
Author: Zipcodestack
Author-email: support@zipcodestack.com
License: MIT
Project-URL: Documentation, https://zipcodestack.com/docs/
Project-URL: Source, https://github.com/everapihq/zipcodestack-python
Project-URL: Tracker, https://github.com/everapihq/zipcodestack-python/issues
Classifier: Programming Language :: Python :: 3
Classifier: License :: OSI Approved :: MIT License
Classifier: Operating System :: OS Independent
Classifier: Programming Language :: Python :: 3 :: Only
Requires-Python: >=3.8
License-File: LICENSE
Requires-Dist: everapi>=0.1.0
Dynamic: author
Dynamic: author-email
Dynamic: classifier
Dynamic: description
Dynamic: description-content-type
Dynamic: home-page
Dynamic: license
Dynamic: license-file
Dynamic: project-url
Dynamic: requires-dist
Dynamic: requires-python
Dynamic: summary
